valueapiconnector/__init__.py
valueapiconnector/lib.py
valueapiconnector-0.1.0.dist-info/METADATA
valueapiconnector-0.1.0.dist-info/WHEEL
valueapiconnector-0.1.0.dist-info/RECORD
