Metadata-Version: 2.4
Name: valueapiconnector
Version: 0.1.0
Summary: A python value api connector
Author-email: Jonas Blatt <jonas@blatts.de>
Requires-Python: >=3.13
Requires-Dist: requests>=2.32.3
